vocoder/__init__.py
vocoder/acoustic_models/wav2vec2.py
vocoder/actions.py
vocoder/app.py
vocoder/attribute_registry.py
vocoder/audio_to_ctc.py
vocoder/audio_utils.py
vocoder/compile_grammar.py
vocoder/dsl.py
vocoder/dsl_grammar.lark
vocoder/dsl_processing.py
vocoder/dsl_to_ast.py
vocoder/exceptions.py
vocoder/grammar.py
vocoder/graphing.py
vocoder/id_generator.py
vocoder/lexicon.py
vocoder/lexicon_registry.py
vocoder/lexicons/__init__.py
vocoder/lexicons/en_frequent.py
vocoder/lexicons/en_frequent.txt
vocoder/lexicons/numbers.py
vocoder/lexicons/python.py
vocoder/math.py
vocoder/namespace.py
vocoder/py.typed
vocoder/simulate_ctc.py
vocoder/soft.py
vocoder/soft_beam_search.py
vocoder/soft_simulate.py
vocoder/token_encoding.py
vocoder/utils.py
vocoder_dictation-0.1.1.dist-info/LICENSE.txt
vocoder_dictation-0.1.1.dist-info/WHEEL
vocoder_dictation-0.1.1.dist-info/METADATA
vocoder_dictation-0.1.1.dist-info/RECORD
